noizze_crawler.py
noizze_crawler-12.dist-info/LICENSE
noizze_crawler-12.dist-info/METADATA
noizze_crawler-12.dist-info/WHEEL
noizze_crawler-12.dist-info/top_level.txt
noizze_crawler-12.dist-info/RECORD
