Metadata-Version: 2.1
Name: noizze-crawler
Version: 12
Summary: A web page crawler which returns (title, og:image, og:description).
Home-page: https://github.com/YUChoe/noizze_crawler
Author: Tom YU Choe
Author-email: yonguk.choe@gmail.com
License: MIT
Platform: UNKNOWN
Classifier: Development Status :: 4 - Beta
Classifier: Intended Audience :: System Administrators
Classifier: Programming Language :: Python :: 3
Classifier: Programming Language :: Python :: 3.4
Classifier: Programming Language :: Python :: 3.6
Classifier: License :: OSI Approved :: MIT License
Classifier: Operating System :: POSIX :: Linux
Requires-Dist: beautifulsoup4 (>=4.5.0)
